<?xml version="1.0" encoding="utf-8"?>
<doctrine-mapping xmlns="http://doctrine-project.org/schemas/orm/doctrine-mapping" xmlns:xsi="http://www.w3.org/2001/XMLSchema-instance" xsi:schemaLocation="http://doctrine-project.org/schemas/orm/doctrine-mapping http://doctrine-project.org/schemas/orm/doctrine-mapping.xsd">
  <entity name="WSServerBundle\Entity\Demandepret" table="demandepret">
    <id name="id" type="integer" column="id">
      <generator strategy="IDENTITY"/>
    </id>
    <field name="idUser" type="integer" column="id_user" nullable="false">
      <options>
        <option name="unsigned"/>
      </options>
    </field>
    <field name="dependsOn" type="integer" column="depends_on" nullable="false">
      <options>
        <option name="unsigned"/>
      </options>
    </field>
    <field name="montantdemande" type="integer" column="montantdemande" nullable="false">
      <options>
        <option name="unsigned"/>
      </options>
    </field>
    <field name="plafond" type="integer" column="plafond" nullable="false">
      <options>
        <option name="unsigned"/>
      </options>
    </field>
  </entity>
</doctrine-mapping>
